bc_python_hcl2-0.4.1.data/scripts/hcl2tojson
hcl2/__init__.py
hcl2/api.py
hcl2/hcl2.lark
hcl2/parser.py
hcl2/py.typed
hcl2/transformer.py
hcl2/version.py
test/__init__.py
test/helpers/__init__.py
test/unit/__init__.py
test/unit/test_load.py
test/unit/test_parse.py
bc_python_hcl2-0.4.1.dist-info/LICENSE
bc_python_hcl2-0.4.1.dist-info/METADATA
bc_python_hcl2-0.4.1.dist-info/WHEEL
bc_python_hcl2-0.4.1.dist-info/top_level.txt
bc_python_hcl2-0.4.1.dist-info/RECORD
