Metadata-Version: 2.1
Name: bc-python-hcl2
Version: 0.4.1
Summary: A parser for HCL2
Home-page: https://github.com/bridgecrewio/python-hcl2
Author: bridgecrew
Author-email: meet@bridgecrew.io
License: MIT
Classifier: Topic :: Software Development :: Libraries :: Python Modules
Classifier: Intended Audience :: Developers
Classifier: License :: OSI Approved :: MIT License
Classifier: Operating System :: OS Independent
Classifier: Programming Language :: Python
Classifier: Programming Language :: Python :: 3
Classifier: Programming Language :: Python :: 3.8
Classifier: Programming Language :: Python :: 3.9
Classifier: Programming Language :: Python :: 3.10
Classifier: Programming Language :: Python :: 3.11
Classifier: Programming Language :: Python :: 3.12
Classifier: Programming Language :: Python :: 3 :: Only
Classifier: Typing :: Typed
Requires-Python: >=3.8
License-File: LICENSE
Requires-Dist: lark>=1.0.0
Requires-Dist: importlib-resources>=2.0.0; python_version < "3.9"
